srl/__init__.py
srl/block.py
srl/byte_buffer.py
srl/byte_utils.py
srl/dat_file_reader.py
srl/main.py
srl/print_utils.py
srl/segment.py
srl/tag.py
dora_sl_evandro_teixeira_tatic-0.0.2.dist-info/LICENSE
dora_sl_evandro_teixeira_tatic-0.0.2.dist-info/METADATA
dora_sl_evandro_teixeira_tatic-0.0.2.dist-info/WHEEL
dora_sl_evandro_teixeira_tatic-0.0.2.dist-info/top_level.txt
dora_sl_evandro_teixeira_tatic-0.0.2.dist-info/RECORD
