Metadata-Version: 2.1
Name: dora-sl-evandro-teixeira-tatic
Version: 0.0.2
Summary: Serverless Reader Poc
Home-page: UNKNOWN
Author: Evandro Teixeira
Author-email: evandro.teixeira@tatic.net
License: UNKNOWN
Platform: UNKNOWN
Classifier: Programming Language :: Python :: 3
Classifier: License :: OSI Approved :: MIT License
Classifier: Operating System :: OS Independent
Requires-Python: >=3.6
